README.rst
setup.py
django_el.egg-info/PKG-INFO
django_el.egg-info/SOURCES.txt
django_el.egg-info/dependency_links.txt
django_el.egg-info/not-zip-safe
django_el.egg-info/top_level.txt
el/__init__.py
el/admin.py
el/apps.py
el/conf.py
el/forms.py
el/index.py
el/managers.py
el/models.py
el/queries.py
el/services.py
el/signals.py
el/tasks.py
el/urls.py
el/utils.py
el/views.py
el/management/__init__.py
el/management/__pycache__/__init__.cpython-34.pyc
el/management/commands/__init__.py
el/management/commands/update_index.py
el/migrations/__init__.py
el/migrations/__pycache__/__init__.cpython-34.pyc
el/static/el/css/el.css
el/static/el/img/.gitkeep
el/static/el/js/el.js
el/templates/el/.gitkeep
el/templatetags/__init__.py
el/templatetags/el_tags.py
el/templatetags/__pycache__/__init__.cpython-34.pyc
el/tests/__init__.py
el/tests/test_models.py