Metadata-Version: 1.1
Name: django-el
Version: 0.2
Summary: Django elasticsearch integration.
Home-page: https://github.com/asyncee/django-el
Author: asyncee
Author-email: UNKNOWN
License: MIT
Download-URL: https://pypi.python.org/pypi/django-el/
Keywords: django elasticsearch
Platform: UNKNOWN
Classifier: Development Status :: 3 - Alpha
Classifier: Environment :: Web Environment
Classifier: Framework :: Django
Classifier: Intended Audience :: Developers
Classifier: License :: OSI Approved :: MIT License
Classifier: Programming Language :: Python
Classifier: Programming Language :: Python :: 3
Classifier: Topic :: Internet :: WWW/HTTP :: Indexing/Search
